<annotation>
	<folder>VOC2008</folder>
	<filename>2008_002442.jpg</filename>
	<source>
		<database>The VOC2008 Database</database>
		<annotation>PASCAL VOC2008</annotation>
		<image>flickr</image>
		<flickrid>n/a</flickrid>
	</source>
	<owner>
		<flickrid>n/a</flickrid>
		<name>n/a</name>
	</owner>
	<size>
		<width>500</width>
		<height>375</height>
		<depth>3</depth>
	</size>
	<segmented>0</segmented>
	<object>
		<name>dog</name>
		<pose>Unspecified</pose>
		<truncated>1</truncated>
		<occluded>1</occluded>
		<bndbox>
			<xmin>5.9132</xmin>
			<ymin>37.5</ymin>
			<xmax>385.8533</xmax>
			<ymax>375</ymax>
		</bndbox>
		<difficult>0</difficult>
	</object>
	<object>
		<name>person</name>
		<pose>Unspecified</pose>
		<truncated>1</truncated>
		<occluded>1</occluded>
		<bndbox>
			<xmin>1</xmin>
			<ymin>1</ymin>
			<xmax>373.2784</xmax>
			<ymax>375</ymax>
		</bndbox>
		<difficult>1</difficult>
	</object>
	<object>
		<name>chair</name>
		<pose>SideFaceLeft</pose>
		<truncated>1</truncated>
		<occluded>0</occluded>
		<bndbox>
			<xmin>296.0329</xmin>
			<ymin>1</ymin>
			<xmax>331.0629</xmax>
			<ymax>40.1946</ymax>
		</bndbox>
		<difficult>0</difficult>
	</object>
	<object>
		<name>chair</name>
		<pose>Unspecified</pose>
		<truncated>1</truncated>
		<occluded>0</occluded>
		<bndbox>
			<xmin>257.4102</xmin>
			<ymin>0</ymin>
			<xmax>291.991</xmax>
			<ymax>39.7455</ymax>
		</bndbox>
		<difficult>0</difficult>
	</object>
	<object>
		<name>chair</name>
		<pose>Rear</pose>
		<truncated>1</truncated>
		<occluded>1</occluded>
		<bndbox>
			<xmin>114.5958</xmin>
			<ymin>12.3503</ymin>
			<xmax>188.6976</xmax>
			<ymax>113.3982</ymax>
		</bndbox>
		<difficult>0</difficult>
	</object>
	<object>
		<name>chair</name>
		<pose>Unspecified</pose>
		<truncated>1</truncated>
		<occluded>0</occluded>
		<bndbox>
			<xmin>65.1946</xmin>
			<ymin>10.5539</ymin>
			<xmax>118.6377</xmax>
			<ymax>140.3443</ymax>
		</bndbox>
		<difficult>0</difficult>
	</object>
	<object>
		<name>chair</name>
		<pose>Unspecified</pose>
		<truncated>1</truncated>
		<occluded>1</occluded>
		<bndbox>
			<xmin>159.506</xmin>
			<ymin>7.8593</ymin>
			<xmax>199.476</xmax>
			<ymax>65.7934</ymax>
		</bndbox>
		<difficult>1</difficult>
	</object>
	<object>
		<name>chair</name>
		<pose>Frontal</pose>
		<truncated>1</truncated>
		<occluded>1</occluded>
		<bndbox>
			<xmin>65.6437</xmin>
			<ymin>0</ymin>
			<xmax>127.6198</xmax>
			<ymax>126.8713</ymax>
		</bndbox>
		<difficult>0</difficult>
	</object>
	<object>
		<name>car</name>
		<pose>Rear</pose>
		<truncated>1</truncated>
		<occluded>1</occluded>
		<bndbox>
			<xmin>359.7446</xmin>
			<ymin>1</ymin>
			<xmax>480.369</xmax>
			<ymax>55.2862</ymax>
		</bndbox>
		<difficult>0</difficult>
	</object>
</annotation>
