<annotation>
	<folder>VOC2008</folder>
	<filename>2008_002566.jpg</filename>
	<source>
		<database>The VOC2008 Database</database>
		<annotation>PASCAL VOC2008</annotation>
		<image>flickr</image>
		<flickrid>n/a</flickrid>
	</source>
	<owner>
		<flickrid>n/a</flickrid>
		<name>n/a</name>
	</owner>
	<size>
		<width>500</width>
		<height>365</height>
		<depth>3</depth>
	</size>
	<segmented>0</segmented>
	<object>
		<name>person</name>
		<pose>SideFaceRight</pose>
		<truncated>0</truncated>
		<occluded>0</occluded>
		<bndbox>
			<xmin>103.1532</xmin>
			<ymin>237.3168</ymin>
			<xmax>144.1545</xmax>
			<ymax>315.754</ymax>
		</bndbox>
		<difficult>0</difficult>
	</object>
	<object>
		<name>person</name>
		<pose>SideFaceLeft</pose>
		<truncated>0</truncated>
		<occluded>1</occluded>
		<bndbox>
			<xmin>90.6746</xmin>
			<ymin>259.1545</ymin>
			<xmax>118.3059</xmax>
			<ymax>311.743</ymax>
		</bndbox>
		<difficult>1</difficult>
	</object>
	<object>
		<name>person</name>
		<pose>Frontal</pose>
		<truncated>0</truncated>
		<occluded>1</occluded>
		<bndbox>
			<xmin>70.174</xmin>
			<ymin>241.7735</ymin>
			<xmax>92.4573</xmax>
			<ymax>306.8407</ymax>
		</bndbox>
		<difficult>0</difficult>
	</object>
	<object>
		<name>person</name>
		<pose>Frontal</pose>
		<truncated>0</truncated>
		<occluded>1</occluded>
		<bndbox>
			<xmin>344.7039</xmin>
			<ymin>223.5012</ymin>
			<xmax>365.6502</xmax>
			<ymax>284.5574</ymax>
		</bndbox>
		<difficult>0</difficult>
	</object>
</annotation>
