<annotation>
	<folder>VOC2008</folder>
	<filename>2008_000309.jpg</filename>
	<source>
		<database>The VOC2008 Database</database>
		<annotation>PASCAL VOC2008</annotation>
		<image>flickr</image>
		<flickrid>n/a</flickrid>
	</source>
	<owner>
		<flickrid>n/a</flickrid>
		<name>n/a</name>
	</owner>
	<size>
		<width>500</width>
		<height>373</height>
		<depth>3</depth>
	</size>
	<segmented>1</segmented>
	<object>
		<name>tvmonitor</name>
		<pose>Frontal</pose>
		<truncated>1</truncated>
		<occluded>1</occluded>
		<bndbox>
			<xmin>1</xmin>
			<ymin>40.4269</ymin>
			<xmax>97.003</xmax>
			<ymax>221.3431</ymax>
		</bndbox>
		<difficult>1</difficult>
	</object>
	<object>
		<name>tvmonitor</name>
		<pose>Frontal</pose>
		<truncated>0</truncated>
		<occluded>0</occluded>
		<bndbox>
			<xmin>240.8892</xmin>
			<ymin>159.1676</ymin>
			<xmax>412.172</xmax>
			<ymax>328.9927</ymax>
		</bndbox>
		<difficult>0</difficult>
	</object>
</annotation>
