<annotation>
	<folder>VOC2008</folder>
	<filename>2008_003452.jpg</filename>
	<source>
		<database>The VOC2008 Database</database>
		<annotation>PASCAL VOC2008</annotation>
		<image>flickr</image>
		<flickrid>n/a</flickrid>
	</source>
	<owner>
		<flickrid>n/a</flickrid>
		<name>n/a</name>
	</owner>
	<size>
		<width>500</width>
		<height>375</height>
		<depth>3</depth>
	</size>
	<segmented>0</segmented>
	<object>
		<name>car</name>
		<pose>SideFaceRight</pose>
		<truncated>0</truncated>
		<occluded>0</occluded>
		<bndbox>
			<xmin>0</xmin>
			<ymin>42.4401</ymin>
			<xmax>476.1228</xmax>
			<ymax>306.512</ymax>
		</bndbox>
		<difficult>0</difficult>
	</object>
	<object>
		<name>car</name>
		<pose>SideFaceRight</pose>
		<truncated>1</truncated>
		<occluded>1</occluded>
		<bndbox>
			<xmin>225.0749</xmin>
			<ymin>33.9072</ymin>
			<xmax>440.6437</xmax>
			<ymax>135.4042</ymax>
		</bndbox>
		<difficult>0</difficult>
	</object>
	<object>
		<name>person</name>
		<pose>Rear</pose>
		<truncated>1</truncated>
		<occluded>0</occluded>
		<bndbox>
			<xmin>435.2545</xmin>
			<ymin>48.2784</ymin>
			<xmax>474.7754</xmax>
			<ymax>137.6497</ymax>
		</bndbox>
		<difficult>0</difficult>
	</object>
	<object>
		<name>person</name>
		<pose>SideFaceLeft</pose>
		<truncated>1</truncated>
		<occluded>1</occluded>
		<bndbox>
			<xmin>376.4222</xmin>
			<ymin>45.5838</ymin>
			<xmax>396.1826</xmax>
			<ymax>94.985</ymax>
		</bndbox>
		<difficult>1</difficult>
	</object>
	<object>
		<name>person</name>
		<pose>Rear</pose>
		<truncated>1</truncated>
		<occluded>0</occluded>
		<bndbox>
			<xmin>188.2485</xmin>
			<ymin>44.6856</ymin>
			<xmax>230.9132</xmax>
			<ymax>84.2066</ymax>
		</bndbox>
		<difficult>0</difficult>
	</object>
	<object>
		<name>person</name>
		<pose>SideFaceRight</pose>
		<truncated>1</truncated>
		<occluded>1</occluded>
		<bndbox>
			<xmin>171.6317</xmin>
			<ymin>44.2365</ymin>
			<xmax>201.7216</xmax>
			<ymax>88.2485</ymax>
		</bndbox>
		<difficult>0</difficult>
	</object>
	<object>
		<name>person</name>
		<pose>Frontal</pose>
		<truncated>1</truncated>
		<occluded>1</occluded>
		<bndbox>
			<xmin>152.3204</xmin>
			<ymin>47.8293</ymin>
			<xmax>175.2246</xmax>
			<ymax>88.2485</ymax>
		</bndbox>
		<difficult>0</difficult>
	</object>
</annotation>
