<annotation>
	<folder>VOC2008</folder>
	<filename>2008_003819.jpg</filename>
	<source>
		<database>The VOC2008 Database</database>
		<annotation>PASCAL VOC2008</annotation>
		<image>flickr</image>
		<flickrid>n/a</flickrid>
	</source>
	<owner>
		<flickrid>n/a</flickrid>
		<name>n/a</name>
	</owner>
	<size>
		<width>500</width>
		<height>375</height>
		<depth>3</depth>
	</size>
	<segmented>0</segmented>
	<object>
		<name>bicycle</name>
		<pose>SideFaceRight</pose>
		<truncated>0</truncated>
		<occluded>1</occluded>
		<bndbox>
			<xmin>293.3383</xmin>
			<ymin>186.1527</ymin>
			<xmax>421.7814</xmax>
			<ymax>260.2545</ymax>
		</bndbox>
		<difficult>0</difficult>
	</object>
	<object>
		<name>bicycle</name>
		<pose>SideFaceRight</pose>
		<truncated>0</truncated>
		<occluded>1</occluded>
		<bndbox>
			<xmin>146.482</xmin>
			<ymin>187.5</ymin>
			<xmax>241.6916</xmax>
			<ymax>253.9671</ymax>
		</bndbox>
		<difficult>0</difficult>
	</object>
	<object>
		<name>bicycle</name>
		<pose>SideFaceRight</pose>
		<truncated>0</truncated>
		<occluded>1</occluded>
		<bndbox>
			<xmin>65.6437</xmin>
			<ymin>187.5</ymin>
			<xmax>136.1527</xmax>
			<ymax>243.6377</ymax>
		</bndbox>
		<difficult>0</difficult>
	</object>
	<object>
		<name>bicycle</name>
		<pose>SideFaceRight</pose>
		<truncated>1</truncated>
		<occluded>1</occluded>
		<bndbox>
			<xmin>1</xmin>
			<ymin>189.2964</ymin>
			<xmax>47.6796</xmax>
			<ymax>241.3922</ymax>
		</bndbox>
		<difficult>0</difficult>
	</object>
	<object>
		<name>person</name>
		<pose>SideFaceRight</pose>
		<truncated>0</truncated>
		<occluded>0</occluded>
		<bndbox>
			<xmin>322.5299</xmin>
			<ymin>134.9551</ymin>
			<xmax>393.488</xmax>
			<ymax>244.5359</ymax>
		</bndbox>
		<difficult>0</difficult>
	</object>
	<object>
		<name>person</name>
		<pose>SideFaceRight</pose>
		<truncated>0</truncated>
		<occluded>0</occluded>
		<bndbox>
			<xmin>160.8533</xmin>
			<ymin>143.488</ymin>
			<xmax>215.1946</xmax>
			<ymax>247.2305</ymax>
		</bndbox>
		<difficult>0</difficult>
	</object>
	<object>
		<name>person</name>
		<pose>SideFaceRight</pose>
		<truncated>0</truncated>
		<occluded>0</occluded>
		<bndbox>
			<xmin>74.6257</xmin>
			<ymin>155.1647</ymin>
			<xmax>114.5958</xmax>
			<ymax>235.1048</ymax>
		</bndbox>
		<difficult>0</difficult>
	</object>
	<object>
		<name>person</name>
		<pose>SideFaceRight</pose>
		<truncated>1</truncated>
		<occluded>0</occluded>
		<bndbox>
			<xmin>1</xmin>
			<ymin>158.3084</ymin>
			<xmax>29.2665</xmax>
			<ymax>217.1407</ymax>
		</bndbox>
		<difficult>0</difficult>
	</object>
	<object>
		<name>person</name>
		<pose>Frontal</pose>
		<truncated>0</truncated>
		<occluded>0</occluded>
		<bndbox>
			<xmin>459.506</xmin>
			<ymin>134.0569</ymin>
			<xmax>486.4521</xmax>
			<ymax>202.3204</ymax>
		</bndbox>
		<difficult>0</difficult>
	</object>
	<object>
		<name>person</name>
		<pose>Frontal</pose>
		<truncated>0</truncated>
		<occluded>0</occluded>
		<bndbox>
			<xmin>430.7635</xmin>
			<ymin>144.8353</ymin>
			<xmax>450.0749</xmax>
			<ymax>200.524</ymax>
		</bndbox>
		<difficult>0</difficult>
	</object>
	<object>
		<name>person</name>
		<pose>Frontal</pose>
		<truncated>0</truncated>
		<occluded>0</occluded>
		<bndbox>
			<xmin>416.3922</xmin>
			<ymin>132.2605</ymin>
			<xmax>433.9072</xmax>
			<ymax>195.5838</ymax>
		</bndbox>
		<difficult>0</difficult>
	</object>
	<object>
		<name>person</name>
		<pose>Frontal</pose>
		<truncated>0</truncated>
		<occluded>0</occluded>
		<bndbox>
			<xmin>392.1407</xmin>
			<ymin>135.4042</ymin>
			<xmax>413.6976</xmax>
			<ymax>197.3802</ymax>
		</bndbox>
		<difficult>0</difficult>
	</object>
	<object>
		<name>person</name>
		<pose>Frontal</pose>
		<truncated>1</truncated>
		<occluded>1</occluded>
		<bndbox>
			<xmin>369.6856</xmin>
			<ymin>152.021</ymin>
			<xmax>389.4461</xmax>
			<ymax>190.1946</ymax>
		</bndbox>
		<difficult>1</difficult>
	</object>
	<object>
		<name>person</name>
		<pose>Unspecified</pose>
		<truncated>0</truncated>
		<occluded>0</occluded>
		<bndbox>
			<xmin>307.2605</xmin>
			<ymin>143.0389</ymin>
			<xmax>321.1826</xmax>
			<ymax>201.4222</ymax>
		</bndbox>
		<difficult>0</difficult>
	</object>
	<object>
		<name>person</name>
		<pose>SideFaceLeft</pose>
		<truncated>0</truncated>
		<occluded>0</occluded>
		<bndbox>
			<xmin>298.7275</xmin>
			<ymin>161.4521</ymin>
			<xmax>309.9551</xmax>
			<ymax>201.8713</ymax>
		</bndbox>
		<difficult>1</difficult>
	</object>
	<object>
		<name>person</name>
		<pose>Unspecified</pose>
		<truncated>0</truncated>
		<occluded>0</occluded>
		<bndbox>
			<xmin>221.482</xmin>
			<ymin>143.9371</ymin>
			<xmax>242.1407</xmax>
			<ymax>195.5838</ymax>
		</bndbox>
		<difficult>0</difficult>
	</object>
	<object>
		<name>person</name>
		<pose>SideFaceLeft</pose>
		<truncated>0</truncated>
		<occluded>0</occluded>
		<bndbox>
			<xmin>122.2305</xmin>
			<ymin>143.0389</ymin>
			<xmax>135.7036</xmax>
			<ymax>187.0509</ymax>
		</bndbox>
		<difficult>1</difficult>
	</object>
	<object>
		<name>person</name>
		<pose>Unspecified</pose>
		<truncated>1</truncated>
		<occluded>1</occluded>
		<bndbox>
			<xmin>108.7575</xmin>
			<ymin>143.488</ymin>
			<xmax>119.0868</xmax>
			<ymax>162.7994</ymax>
		</bndbox>
		<difficult>1</difficult>
	</object>
	<object>
		<name>person</name>
		<pose>Unspecified</pose>
		<truncated>1</truncated>
		<occluded>1</occluded>
		<bndbox>
			<xmin>105.6138</xmin>
			<ymin>153.8174</ymin>
			<xmax>121.7814</xmax>
			<ymax>191.0928</ymax>
		</bndbox>
		<difficult>1</difficult>
	</object>
	<object>
		<name>person</name>
		<pose>Unspecified</pose>
		<truncated>0</truncated>
		<occluded>0</occluded>
		<bndbox>
			<xmin>58.4581</xmin>
			<ymin>154.7156</ymin>
			<xmax>68.7874</xmax>
			<ymax>196.0329</ymax>
		</bndbox>
		<difficult>0</difficult>
	</object>
	<object>
		<name>person</name>
		<pose>Unspecified</pose>
		<truncated>0</truncated>
		<occluded>0</occluded>
		<bndbox>
			<xmin>47.2305</xmin>
			<ymin>154.2665</ymin>
			<xmax>58.4581</xmax>
			<ymax>196.482</ymax>
		</bndbox>
		<difficult>0</difficult>
	</object>
	<object>
		<name>person</name>
		<pose>Unspecified</pose>
		<truncated>1</truncated>
		<occluded>0</occluded>
		<bndbox>
			<xmin>490.9431</xmin>
			<ymin>132.2605</ymin>
			<xmax>500</xmax>
			<ymax>191.0928</ymax>
		</bndbox>
		<difficult>1</difficult>
	</object>
</annotation>
