<annotation>
	<folder>VOC2008</folder>
	<filename>2008_004053.jpg</filename>
	<source>
		<database>The VOC2008 Database</database>
		<annotation>PASCAL VOC2008</annotation>
		<image>flickr</image>
		<flickrid>n/a</flickrid>
	</source>
	<owner>
		<flickrid>n/a</flickrid>
		<name>n/a</name>
	</owner>
	<size>
		<width>500</width>
		<height>375</height>
		<depth>3</depth>
	</size>
	<segmented>0</segmented>
	<object>
		<name>person</name>
		<pose>SideFaceLeft</pose>
		<truncated>1</truncated>
		<occluded>1</occluded>
		<bndbox>
			<xmin>306.4366</xmin>
			<ymin>67.6306</ymin>
			<xmax>500</xmax>
			<ymax>375</ymax>
		</bndbox>
		<difficult>1</difficult>
	</object>
	<object>
		<name>person</name>
		<pose>Unspecified</pose>
		<truncated>1</truncated>
		<occluded>1</occluded>
		<bndbox>
			<xmin>201.0261</xmin>
			<ymin>125.4664</ymin>
			<xmax>327.8918</xmax>
			<ymax>344.6828</ymax>
		</bndbox>
		<difficult>0</difficult>
	</object>
	<object>
		<name>person</name>
		<pose>Rear</pose>
		<truncated>1</truncated>
		<occluded>1</occluded>
		<bndbox>
			<xmin>107.7425</xmin>
			<ymin>161.847</ymin>
			<xmax>160.9142</xmax>
			<ymax>240.2052</ymax>
		</bndbox>
		<difficult>1</difficult>
	</object>
	<object>
		<name>person</name>
		<pose>Rear</pose>
		<truncated>1</truncated>
		<occluded>1</occluded>
		<bndbox>
			<xmin>86.2873</xmin>
			<ymin>128.2649</ymin>
			<xmax>254.1978</xmax>
			<ymax>290.5784</ymax>
		</bndbox>
		<difficult>0</difficult>
	</object>
	<object>
		<name>person</name>
		<pose>Rear</pose>
		<truncated>1</truncated>
		<occluded>1</occluded>
		<bndbox>
			<xmin>60.1679</xmin>
			<ymin>159.0485</ymin>
			<xmax>118.9366</xmax>
			<ymax>248.6007</ymax>
		</bndbox>
		<difficult>0</difficult>
	</object>
	<object>
		<name>person</name>
		<pose>Rear</pose>
		<truncated>0</truncated>
		<occluded>1</occluded>
		<bndbox>
			<xmin>27.5187</xmin>
			<ymin>153.4515</ymin>
			<xmax>86.2873</xmax>
			<ymax>230.8769</ymax>
		</bndbox>
		<difficult>0</difficult>
	</object>
	<object>
		<name>person</name>
		<pose>Rear</pose>
		<truncated>1</truncated>
		<occluded>1</occluded>
		<bndbox>
			<xmin>15.3918</xmin>
			<ymin>99.347</ymin>
			<xmax>76.0261</xmax>
			<ymax>198.2276</ymax>
		</bndbox>
		<difficult>0</difficult>
	</object>
	<object>
		<name>boat</name>
		<pose>Rear</pose>
		<truncated>1</truncated>
		<occluded>1</occluded>
		<bndbox>
			<xmin>22.8545</xmin>
			<ymin>187.9664</ymin>
			<xmax>455.6903</xmax>
			<ymax>375</ymax>
		</bndbox>
		<difficult>0</difficult>
	</object>
</annotation>
