<annotation>
	<folder>VOC2008</folder>
	<filename>2008_004084.jpg</filename>
	<source>
		<database>The VOC2008 Database</database>
		<annotation>PASCAL VOC2008</annotation>
		<image>flickr</image>
		<flickrid>n/a</flickrid>
	</source>
	<owner>
		<flickrid>n/a</flickrid>
		<name>n/a</name>
	</owner>
	<size>
		<width>500</width>
		<height>333</height>
		<depth>3</depth>
	</size>
	<segmented>0</segmented>
	<object>
		<name>motorbike</name>
		<pose>SideFaceLeft</pose>
		<truncated>1</truncated>
		<occluded>0</occluded>
		<bndbox>
			<xmin>458.0373</xmin>
			<ymin>179.8215</ymin>
			<xmax>500</xmax>
			<ymax>245.9849</ymax>
		</bndbox>
		<difficult>0</difficult>
	</object>
	<object>
		<name>motorbike</name>
		<pose>SideFaceLeft</pose>
		<truncated>1</truncated>
		<occluded>1</occluded>
		<bndbox>
			<xmin>39.2984</xmin>
			<ymin>158.0631</ymin>
			<xmax>119.2274</xmax>
			<ymax>280.1767</ymax>
		</bndbox>
		<difficult>0</difficult>
	</object>
	<object>
		<name>motorbike</name>
		<pose>Rear</pose>
		<truncated>1</truncated>
		<occluded>1</occluded>
		<bndbox>
			<xmin>2.4423</xmin>
			<ymin>207.7966</ymin>
			<xmax>31.3055</xmax>
			<ymax>289.9458</ymax>
		</bndbox>
		<difficult>1</difficult>
	</object>
	<object>
		<name>motorbike</name>
		<pose>Rear</pose>
		<truncated>1</truncated>
		<occluded>1</occluded>
		<bndbox>
			<xmin>69.4938</xmin>
			<ymin>190.4787</ymin>
			<xmax>249.778</xmax>
			<ymax>333</ymax>
		</bndbox>
		<difficult>1</difficult>
	</object>
	<object>
		<name>motorbike</name>
		<pose>SideFaceRight</pose>
		<truncated>1</truncated>
		<occluded>1</occluded>
		<bndbox>
			<xmin>232.46</xmin>
			<ymin>182.9298</ymin>
			<xmax>481.5719</xmax>
			<ymax>333</ymax>
		</bndbox>
		<difficult>0</difficult>
	</object>
	<object>
		<name>person</name>
		<pose>SideFaceRight</pose>
		<truncated>1</truncated>
		<occluded>0</occluded>
		<bndbox>
			<xmin>0</xmin>
			<ymin>120.7629</ymin>
			<xmax>35.302</xmax>
			<ymax>325.9139</ymax>
		</bndbox>
		<difficult>0</difficult>
	</object>
	<object>
		<name>person</name>
		<pose>Unspecified</pose>
		<truncated>1</truncated>
		<occluded>1</occluded>
		<bndbox>
			<xmin>8.659</xmin>
			<ymin>132.3082</ymin>
			<xmax>40.6306</xmax>
			<ymax>225.1146</ymax>
		</bndbox>
		<difficult>1</difficult>
	</object>
	<object>
		<name>person</name>
		<pose>SideFaceRight</pose>
		<truncated>1</truncated>
		<occluded>0</occluded>
		<bndbox>
			<xmin>318.6057</xmin>
			<ymin>133.6403</ymin>
			<xmax>340.3641</xmax>
			<ymax>175.381</ymax>
		</bndbox>
		<difficult>0</difficult>
	</object>
	<object>
		<name>person</name>
		<pose>Frontal</pose>
		<truncated>1</truncated>
		<occluded>1</occluded>
		<bndbox>
			<xmin>334.5915</xmin>
			<ymin>140.3011</ymin>
			<xmax>347.913</xmax>
			<ymax>169.1643</ymax>
		</bndbox>
		<difficult>1</difficult>
	</object>
	<object>
		<name>person</name>
		<pose>Rear</pose>
		<truncated>1</truncated>
		<occluded>1</occluded>
		<bndbox>
			<xmin>79.7069</xmin>
			<ymin>125.2034</ymin>
			<xmax>232.46</xmax>
			<ymax>333</ymax>
		</bndbox>
		<difficult>0</difficult>
	</object>
	<object>
		<name>person</name>
		<pose>SideFaceRight</pose>
		<truncated>0</truncated>
		<occluded>1</occluded>
		<bndbox>
			<xmin>319.4938</xmin>
			<ymin>141.1892</ymin>
			<xmax>416.7407</xmax>
			<ymax>333</ymax>
		</bndbox>
		<difficult>0</difficult>
	</object>
	<object>
		<name>person</name>
		<pose>Rear</pose>
		<truncated>1</truncated>
		<occluded>1</occluded>
		<bndbox>
			<xmin>247.6348</xmin>
			<ymin>141.6656</ymin>
			<xmax>311.0218</xmax>
			<ymax>246.2067</ymax>
		</bndbox>
		<difficult>0</difficult>
	</object>
</annotation>
