<annotation>
	<folder>VOC2008</folder>
	<filename>2008_004398.jpg</filename>
	<source>
		<database>The VOC2008 Database</database>
		<annotation>PASCAL VOC2008</annotation>
		<image>flickr</image>
		<flickrid>n/a</flickrid>
	</source>
	<owner>
		<flickrid>n/a</flickrid>
		<name>n/a</name>
	</owner>
	<size>
		<width>249</width>
		<height>363</height>
		<depth>3</depth>
	</size>
	<segmented>0</segmented>
	<object>
		<name>sofa</name>
		<pose>Rear</pose>
		<truncated>1</truncated>
		<occluded>1</occluded>
		<bndbox>
			<xmin>0</xmin>
			<ymin>139.3938</ymin>
			<xmax>249</xmax>
			<ymax>327.7637</ymax>
		</bndbox>
		<difficult>1</difficult>
	</object>
	<object>
		<name>person</name>
		<pose>Frontal</pose>
		<truncated>1</truncated>
		<occluded>1</occluded>
		<bndbox>
			<xmin>99.4579</xmin>
			<ymin>84.4341</ymin>
			<xmax>192.5348</xmax>
			<ymax>359.6758</ymax>
		</bndbox>
		<difficult>0</difficult>
	</object>
	<object>
		<name>person</name>
		<pose>Frontal</pose>
		<truncated>1</truncated>
		<occluded>1</occluded>
		<bndbox>
			<xmin>0</xmin>
			<ymin>132.3022</ymin>
			<xmax>161.9524</xmax>
			<ymax>363</ymax>
		</bndbox>
		<difficult>0</difficult>
	</object>
	<object>
		<name>person</name>
		<pose>Frontal</pose>
		<truncated>1</truncated>
		<occluded>1</occluded>
		<bndbox>
			<xmin>9.9267</xmin>
			<ymin>222.7198</ymin>
			<xmax>120.7326</xmax>
			<ymax>363</ymax>
		</bndbox>
		<difficult>0</difficult>
	</object>
</annotation>
