<annotation>
	<folder>VOC2008</folder>
	<filename>2008_004501.jpg</filename>
	<source>
		<database>The VOC2008 Database</database>
		<annotation>PASCAL VOC2008</annotation>
		<image>flickr</image>
		<flickrid>n/a</flickrid>
	</source>
	<owner>
		<flickrid>n/a</flickrid>
		<name>n/a</name>
	</owner>
	<size>
		<width>500</width>
		<height>375</height>
		<depth>3</depth>
	</size>
	<segmented>0</segmented>
	<object>
		<name>chair</name>
		<pose>SideFaceLeft</pose>
		<truncated>1</truncated>
		<occluded>0</occluded>
		<bndbox>
			<xmin>360.7036</xmin>
			<ymin>224.7754</ymin>
			<xmax>426.7216</xmax>
			<ymax>375</ymax>
		</bndbox>
		<difficult>1</difficult>
	</object>
	<object>
		<name>person</name>
		<pose>SideFaceLeft</pose>
		<truncated>1</truncated>
		<occluded>0</occluded>
		<bndbox>
			<xmin>177.9192</xmin>
			<ymin>82.4102</ymin>
			<xmax>371.482</xmax>
			<ymax>375</ymax>
		</bndbox>
		<difficult>0</difficult>
	</object>
	<object>
		<name>tvmonitor</name>
		<pose>Unspecified</pose>
		<truncated>1</truncated>
		<occluded>0</occluded>
		<bndbox>
			<xmin>1</xmin>
			<ymin>119.2365</ymin>
			<xmax>87.6497</xmax>
			<ymax>275.524</ymax>
		</bndbox>
		<difficult>0</difficult>
	</object>
	<object>
		<name>bottle</name>
		<pose>Unspecified</pose>
		<truncated>0</truncated>
		<occluded>0</occluded>
		<bndbox>
			<xmin>283.009</xmin>
			<ymin>78.8174</ymin>
			<xmax>310.4042</xmax>
			<ymax>172.2305</ymax>
		</bndbox>
		<difficult>0</difficult>
	</object>
	<object>
		<name>person</name>
		<pose>Unspecified</pose>
		<truncated>1</truncated>
		<occluded>1</occluded>
		<bndbox>
			<xmin>414.5958</xmin>
			<ymin>4.7156</ymin>
			<xmax>494.985</xmax>
			<ymax>85.5539</ymax>
		</bndbox>
		<difficult>0</difficult>
	</object>
	<object>
		<name>chair</name>
		<pose>Unspecified</pose>
		<truncated>1</truncated>
		<occluded>0</occluded>
		<bndbox>
			<xmin>443.3383</xmin>
			<ymin>52.3204</ymin>
			<xmax>500</xmax>
			<ymax>139.4461</ymax>
		</bndbox>
		<difficult>1</difficult>
	</object>
</annotation>
