<annotation>
	<folder>VOC2008</folder>
	<filename>2008_004624.jpg</filename>
	<source>
		<database>The VOC2008 Database</database>
		<annotation>PASCAL VOC2008</annotation>
		<image>flickr</image>
		<flickrid>n/a</flickrid>
	</source>
	<owner>
		<flickrid>n/a</flickrid>
		<name>n/a</name>
	</owner>
	<size>
		<width>500</width>
		<height>354</height>
		<depth>3</depth>
	</size>
	<segmented>1</segmented>
	<object>
		<name>horse</name>
		<pose>SideFaceLeft</pose>
		<truncated>0</truncated>
		<occluded>0</occluded>
		<bndbox>
			<xmin>150.3108</xmin>
			<ymin>110.3925</ymin>
			<xmax>437.167</xmax>
			<ymax>276.0231</ymax>
		</bndbox>
		<difficult>0</difficult>
	</object>
</annotation>
