<annotation>
	<folder>VOC2008</folder>
	<filename>2008_004763.jpg</filename>
	<source>
		<database>The VOC2008 Database</database>
		<annotation>PASCAL VOC2008</annotation>
		<image>flickr</image>
		<flickrid>n/a</flickrid>
	</source>
	<owner>
		<flickrid>n/a</flickrid>
		<name>n/a</name>
	</owner>
	<size>
		<width>500</width>
		<height>334</height>
		<depth>3</depth>
	</size>
	<segmented>0</segmented>
	<object>
		<name>bird</name>
		<pose>SideFaceRight</pose>
		<truncated>0</truncated>
		<occluded>0</occluded>
		<bndbox>
			<xmin>290.4519</xmin>
			<ymin>142.5831</ymin>
			<xmax>308.6735</xmax>
			<ymax>158.6181</ymax>
		</bndbox>
		<difficult>0</difficult>
	</object>
	<object>
		<name>dog</name>
		<pose>SideFaceLeft</pose>
		<truncated>0</truncated>
		<occluded>0</occluded>
		<bndbox>
			<xmin>315.9621</xmin>
			<ymin>200.8921</ymin>
			<xmax>380.102</xmax>
			<ymax>259.2012</ymax>
		</bndbox>
		<difficult>0</difficult>
	</object>
	<object>
		<name>dog</name>
		<pose>Unspecified</pose>
		<truncated>0</truncated>
		<occluded>0</occluded>
		<bndbox>
			<xmin>202.9883</xmin>
			<ymin>197.9767</ymin>
			<xmax>248.1778</xmax>
			<ymax>251.9125</ymax>
		</bndbox>
		<difficult>0</difficult>
	</object>
</annotation>
