<annotation>
	<folder>VOC2008</folder>
	<filename>2008_005429.jpg</filename>
	<source>
		<database>The VOC2008 Database</database>
		<annotation>PASCAL VOC2008</annotation>
		<image>flickr</image>
		<flickrid>n/a</flickrid>
	</source>
	<owner>
		<flickrid>n/a</flickrid>
		<name>n/a</name>
	</owner>
	<size>
		<width>500</width>
		<height>370</height>
		<depth>3</depth>
	</size>
	<segmented>0</segmented>
	<object>
		<name>motorbike</name>
		<pose>SideFaceRight</pose>
		<truncated>0</truncated>
		<occluded>1</occluded>
		<bndbox>
			<xmin>65.9414</xmin>
			<ymin>144.1474</ymin>
			<xmax>406.9716</xmax>
			<ymax>343.0817</ymax>
		</bndbox>
		<difficult>0</difficult>
	</object>
	<object>
		<name>motorbike</name>
		<pose>SideFaceRight</pose>
		<truncated>1</truncated>
		<occluded>0</occluded>
		<bndbox>
			<xmin>340.3641</xmin>
			<ymin>122.389</ymin>
			<xmax>500</xmax>
			<ymax>240.9503</ymax>
		</bndbox>
		<difficult>0</difficult>
	</object>
	<object>
		<name>person</name>
		<pose>SideFaceRight</pose>
		<truncated>0</truncated>
		<occluded>1</occluded>
		<bndbox>
			<xmin>156.5275</xmin>
			<ymin>46.4565</ymin>
			<xmax>291.0746</xmax>
			<ymax>370</ymax>
		</bndbox>
		<difficult>0</difficult>
	</object>
	<object>
		<name>person</name>
		<pose>Frontal</pose>
		<truncated>0</truncated>
		<occluded>1</occluded>
		<bndbox>
			<xmin>261.3233</xmin>
			<ymin>5.6039</ymin>
			<xmax>342.1403</xmax>
			<ymax>237.3979</ymax>
		</bndbox>
		<difficult>0</difficult>
	</object>
	<object>
		<name>person</name>
		<pose>SideFaceRight</pose>
		<truncated>1</truncated>
		<occluded>1</occluded>
		<bndbox>
			<xmin>438.0551</xmin>
			<ymin>0.27531</ymin>
			<xmax>478.0195</xmax>
			<ymax>141.4831</ymax>
		</bndbox>
		<difficult>0</difficult>
	</object>
	<object>
		<name>person</name>
		<pose>Frontal</pose>
		<truncated>1</truncated>
		<occluded>1</occluded>
		<bndbox>
			<xmin>477.5755</xmin>
			<ymin>25.1421</ymin>
			<xmax>500</xmax>
			<ymax>132.1581</ymax>
		</bndbox>
		<difficult>0</difficult>
	</object>
</annotation>
