<annotation>
	<folder>VOC2008</folder>
	<filename>2008_006500.jpg</filename>
	<source>
		<database>The VOC2008 Database</database>
		<annotation>PASCAL VOC2008</annotation>
		<image>flickr</image>
		<flickrid>n/a</flickrid>
	</source>
	<owner>
		<flickrid>n/a</flickrid>
		<name>n/a</name>
	</owner>
	<size>
		<width>500</width>
		<height>375</height>
		<depth>3</depth>
	</size>
	<segmented>0</segmented>
	<object>
		<name>boat</name>
		<pose>SideFaceRight</pose>
		<truncated>0</truncated>
		<occluded>0</occluded>
		<bndbox>
			<xmin>141.7185</xmin>
			<ymin>198.3865</ymin>
			<xmax>287.5194</xmax>
			<ymax>215.8826</ymax>
		</bndbox>
		<difficult>0</difficult>
	</object>
	<object>
		<name>boat</name>
		<pose>SideFaceRight</pose>
		<truncated>0</truncated>
		<occluded>0</occluded>
		<bndbox>
			<xmin>165.0467</xmin>
			<ymin>184.7784</ymin>
			<xmax>191.4852</xmax>
			<ymax>196.0537</ymax>
		</bndbox>
		<difficult>0</difficult>
	</object>
	<object>
		<name>person</name>
		<pose>SideFaceLeft</pose>
		<truncated>1</truncated>
		<occluded>0</occluded>
		<bndbox>
			<xmin>250.5832</xmin>
			<ymin>200.3305</ymin>
			<xmax>257.9705</xmax>
			<ymax>210.4393</ymax>
		</bndbox>
		<difficult>1</difficult>
	</object>
	<object>
		<name>person</name>
		<pose>SideFaceLeft</pose>
		<truncated>1</truncated>
		<occluded>0</occluded>
		<bndbox>
			<xmin>237.3639</xmin>
			<ymin>199.5529</ymin>
			<xmax>244.7512</xmax>
			<ymax>208.8841</ymax>
		</bndbox>
		<difficult>1</difficult>
	</object>
	<object>
		<name>person</name>
		<pose>SideFaceLeft</pose>
		<truncated>1</truncated>
		<occluded>0</occluded>
		<bndbox>
			<xmin>226.0886</xmin>
			<ymin>200.3305</ymin>
			<xmax>234.2535</xmax>
			<ymax>210.0505</ymax>
		</bndbox>
		<difficult>1</difficult>
	</object>
	<object>
		<name>person</name>
		<pose>SideFaceLeft</pose>
		<truncated>1</truncated>
		<occluded>0</occluded>
		<bndbox>
			<xmin>215.591</xmin>
			<ymin>199.5529</ymin>
			<xmax>221.423</xmax>
			<ymax>208.1065</ymax>
		</bndbox>
		<difficult>1</difficult>
	</object>
	<object>
		<name>person</name>
		<pose>SideFaceLeft</pose>
		<truncated>1</truncated>
		<occluded>0</occluded>
		<bndbox>
			<xmin>201.2053</xmin>
			<ymin>199.9417</ymin>
			<xmax>207.4261</xmax>
			<ymax>208.1065</ymax>
		</bndbox>
		<difficult>1</difficult>
	</object>
	<object>
		<name>person</name>
		<pose>SideFaceLeft</pose>
		<truncated>1</truncated>
		<occluded>0</occluded>
		<bndbox>
			<xmin>189.5412</xmin>
			<ymin>199.1641</ymin>
			<xmax>196.9285</xmax>
			<ymax>207.7177</ymax>
		</bndbox>
		<difficult>1</difficult>
	</object>
	<object>
		<name>person</name>
		<pose>SideFaceLeft</pose>
		<truncated>1</truncated>
		<occluded>0</occluded>
		<bndbox>
			<xmin>180.9876</xmin>
			<ymin>199.1641</ymin>
			<xmax>187.986</xmax>
			<ymax>207.3289</ymax>
		</bndbox>
		<difficult>1</difficult>
	</object>
	<object>
		<name>person</name>
		<pose>SideFaceLeft</pose>
		<truncated>1</truncated>
		<occluded>0</occluded>
		<bndbox>
			<xmin>170.1011</xmin>
			<ymin>198.3865</ymin>
			<xmax>177.8771</xmax>
			<ymax>206.1625</ymax>
		</bndbox>
		<difficult>1</difficult>
	</object>
	<object>
		<name>person</name>
		<pose>SideFaceRight</pose>
		<truncated>1</truncated>
		<occluded>0</occluded>
		<bndbox>
			<xmin>156.1042</xmin>
			<ymin>198.7753</ymin>
			<xmax>164.2691</xmax>
			<ymax>206.5513</ymax>
		</bndbox>
		<difficult>1</difficult>
	</object>
	<object>
		<name>person</name>
		<pose>Unspecified</pose>
		<truncated>1</truncated>
		<occluded>0</occluded>
		<bndbox>
			<xmin>171.6563</xmin>
			<ymin>186.3336</ymin>
			<xmax>176.7107</xmax>
			<ymax>193.332</ymax>
		</bndbox>
		<difficult>1</difficult>
	</object>
	<object>
		<name>person</name>
		<pose>Unspecified</pose>
		<truncated>1</truncated>
		<occluded>0</occluded>
		<bndbox>
			<xmin>177.8771</xmin>
			<ymin>185.556</ymin>
			<xmax>184.098</xmax>
			<ymax>193.332</ymax>
		</bndbox>
		<difficult>1</difficult>
	</object>
</annotation>
