<annotation>
	<folder>VOC2008</folder>
	<filename>2008_006762.jpg</filename>
	<source>
		<database>The VOC2008 Database</database>
		<annotation>PASCAL VOC2008</annotation>
		<image>flickr</image>
		<flickrid>n/a</flickrid>
	</source>
	<owner>
		<flickrid>n/a</flickrid>
		<name>n/a</name>
	</owner>
	<size>
		<width>500</width>
		<height>375</height>
		<depth>3</depth>
	</size>
	<segmented>0</segmented>
	<object>
		<name>car</name>
		<pose>SideFaceRight</pose>
		<truncated>0</truncated>
		<occluded>0</occluded>
		<bndbox>
			<xmin>131.9963</xmin>
			<ymin>140.3918</ymin>
			<xmax>403.4515</xmax>
			<ymax>305.5037</ymax>
		</bndbox>
		<difficult>0</difficult>
	</object>
	<object>
		<name>car</name>
		<pose>SideFaceLeft</pose>
		<truncated>1</truncated>
		<occluded>1</occluded>
		<bndbox>
			<xmin>364.2724</xmin>
			<ymin>129.1978</ymin>
			<xmax>395.9888</xmax>
			<ymax>143.1903</ymax>
		</bndbox>
		<difficult>0</difficult>
	</object>
	<object>
		<name>car</name>
		<pose>SideFaceRight</pose>
		<truncated>1</truncated>
		<occluded>1</occluded>
		<bndbox>
			<xmin>131.9963</xmin>
			<ymin>110.541</ymin>
			<xmax>166.5112</xmax>
			<ymax>123.6007</ymax>
		</bndbox>
		<difficult>0</difficult>
	</object>
	<object>
		<name>car</name>
		<pose>Rear</pose>
		<truncated>0</truncated>
		<occluded>0</occluded>
		<bndbox>
			<xmin>82.556</xmin>
			<ymin>105.8769</ymin>
			<xmax>102.1455</xmax>
			<ymax>119.8694</ymax>
		</bndbox>
		<difficult>1</difficult>
	</object>
	<object>
		<name>car</name>
		<pose>Unspecified</pose>
		<truncated>0</truncated>
		<occluded>0</occluded>
		<bndbox>
			<xmin>49.0269</xmin>
			<ymin>107.5599</ymin>
			<xmax>58.4581</xmax>
			<ymax>113.3982</ymax>
		</bndbox>
		<difficult>1</difficult>
	</object>
	<object>
		<name>person</name>
		<pose>Frontal</pose>
		<truncated>0</truncated>
		<occluded>0</occluded>
		<bndbox>
			<xmin>289.2964</xmin>
			<ymin>118.7874</ymin>
			<xmax>298.7275</xmax>
			<ymax>134.506</ymax>
		</bndbox>
		<difficult>1</difficult>
	</object>
</annotation>
