<annotation>
	<folder>VOC2008</folder>
	<filename>2008_006817.jpg</filename>
	<source>
		<database>The VOC2008 Database</database>
		<annotation>PASCAL VOC2008</annotation>
		<image>flickr</image>
		<flickrid>n/a</flickrid>
	</source>
	<owner>
		<flickrid>n/a</flickrid>
		<name>n/a</name>
	</owner>
	<size>
		<width>500</width>
		<height>332</height>
		<depth>3</depth>
	</size>
	<segmented>0</segmented>
	<object>
		<name>cat</name>
		<pose>SideFaceLeft</pose>
		<truncated>0</truncated>
		<occluded>0</occluded>
		<bndbox>
			<xmin>229.3517</xmin>
			<ymin>126.9236</ymin>
			<xmax>386.5453</xmax>
			<ymax>217.0657</ymax>
		</bndbox>
		<difficult>0</difficult>
	</object>
	<object>
		<name>cat</name>
		<pose>Frontal</pose>
		<truncated>0</truncated>
		<occluded>0</occluded>
		<bndbox>
			<xmin>148.9787</xmin>
			<ymin>103.389</ymin>
			<xmax>210.2575</xmax>
			<ymax>187.3144</ymax>
		</bndbox>
		<difficult>0</difficult>
	</object>
	<object>
		<name>cat</name>
		<pose>Frontal</pose>
		<truncated>0</truncated>
		<occluded>1</occluded>
		<bndbox>
			<xmin>199.6004</xmin>
			<ymin>109.6057</ymin>
			<xmax>271.0924</xmax>
			<ymax>191.7549</ymax>
		</bndbox>
		<difficult>0</difficult>
	</object>
</annotation>
