<annotation>
	<folder>VOC2008</folder>
	<filename>2008_008588.jpg</filename>
	<source>
		<database>The VOC2008 Database</database>
		<annotation>PASCAL VOC2008</annotation>
		<image>flickr</image>
		<flickrid>n/a</flickrid>
	</source>
	<owner>
		<flickrid>n/a</flickrid>
		<name>n/a</name>
	</owner>
	<size>
		<width>500</width>
		<height>375</height>
		<depth>3</depth>
	</size>
	<segmented>0</segmented>
	<object>
		<name>sofa</name>
		<pose>Frontal</pose>
		<truncated>1</truncated>
		<occluded>1</occluded>
		<bndbox>
			<xmin>0</xmin>
			<ymin>133.1587</ymin>
			<xmax>500</xmax>
			<ymax>375</ymax>
		</bndbox>
		<difficult>0</difficult>
	</object>
	<object>
		<name>person</name>
		<pose>Frontal</pose>
		<truncated>1</truncated>
		<occluded>0</occluded>
		<bndbox>
			<xmin>281.2126</xmin>
			<ymin>0.67365</ymin>
			<xmax>500</xmax>
			<ymax>375</ymax>
		</bndbox>
		<difficult>0</difficult>
	</object>
	<object>
		<name>person</name>
		<pose>Frontal</pose>
		<truncated>1</truncated>
		<occluded>1</occluded>
		<bndbox>
			<xmin>59.8054</xmin>
			<ymin>80.6138</ymin>
			<xmax>235.4042</xmax>
			<ymax>375</ymax>
		</bndbox>
		<difficult>0</difficult>
	</object>
	<object>
		<name>bottle</name>
		<pose>Unspecified</pose>
		<truncated>1</truncated>
		<occluded>1</occluded>
		<bndbox>
			<xmin>223.2784</xmin>
			<ymin>356.3623</ymin>
			<xmax>248.8772</xmax>
			<ymax>375</ymax>
		</bndbox>
		<difficult>1</difficult>
	</object>
</annotation>
