<annotation>
	<folder>VOC2008</folder>
	<filename>2008_001055.jpg</filename>
	<source>
		<database>The VOC2008 Database</database>
		<annotation>PASCAL VOC2008</annotation>
		<image>flickr</image>
		<flickrid>n/a</flickrid>
	</source>
	<owner>
		<flickrid>n/a</flickrid>
		<name>n/a</name>
	</owner>
	<size>
		<width>500</width>
		<height>375</height>
		<depth>3</depth>
	</size>
	<segmented>0</segmented>
	<object>
		<name>person</name>
		<pose>Frontal</pose>
		<truncated>1</truncated>
		<occluded>1</occluded>
		<bndbox>
			<xmin>188.2485</xmin>
			<ymin>77.9192</ymin>
			<xmax>287.9491</xmax>
			<ymax>258.4581</ymax>
		</bndbox>
		<difficult>0</difficult>
	</object>
	<object>
		<name>person</name>
		<pose>Unspecified</pose>
		<truncated>1</truncated>
		<occluded>1</occluded>
		<bndbox>
			<xmin>152.3204</xmin>
			<ymin>168.6377</ymin>
			<xmax>279.8653</xmax>
			<ymax>375</ymax>
		</bndbox>
		<difficult>0</difficult>
	</object>
	<object>
		<name>person</name>
		<pose>Frontal</pose>
		<truncated>1</truncated>
		<occluded>1</occluded>
		<bndbox>
			<xmin>404.2665</xmin>
			<ymin>2.021</ymin>
			<xmax>500</xmax>
			<ymax>156.0629</ymax>
		</bndbox>
		<difficult>0</difficult>
	</object>
	<object>
		<name>person</name>
		<pose>Unspecified</pose>
		<truncated>1</truncated>
		<occluded>0</occluded>
		<bndbox>
			<xmin>180.6138</xmin>
			<ymin>50.0749</ymin>
			<xmax>452.7695</xmax>
			<ymax>375</ymax>
		</bndbox>
		<difficult>0</difficult>
	</object>
</annotation>
